mlarena/__init__.py
mlarena/pipeline.py
mlarena/preprocessor.py
mlarena/utils/__init__.py
mlarena/utils/data_utils.py
mlarena/utils/io_utils.py
mlarena/utils/model_utils.py
mlarena/utils/plot_utils.py
mlarena/utils/stats_utils.py
mlarena-0.5.1.dist-info/METADATA
mlarena-0.5.1.dist-info/WHEEL
mlarena-0.5.1.dist-info/licenses/LICENSE
mlarena-0.5.1.dist-info/RECORD
