Metadata-Version: 2.4
Name: mlarena
Version: 0.5.1
Summary: An algorithm-agnostic machine learning toolkit for model training, diagnostics and optimization
License: MIT
License-File: LICENSE
Keywords: machine-learning,data-science,preprocessing,pipeline
Author: Mena Wang
Author-email: ningwang25@gmail.com
Requires-Python: >=3.10,<3.14
Classifier: Development Status :: 3 - Alpha
Classifier: Intended Audience :: Science/Research
Classifier: License :: OSI Approved :: MIT License
Classifier: Programming Language :: Python :: 3
Classifier: Programming Language :: Python :: 3.10
Classifier: Programming Language :: Python :: 3.11
Classifier: Programming Language :: Python :: 3.12
Classifier: Programming Language :: Python :: 3.13
Classifier: Topic :: Scientific/Engineering :: Artificial Intelligence
Provides-Extra: demo-dependencies
Requires-Dist: lightgbm (>=4.3.0) ; extra == "demo-dependencies"
Requires-Dist: matplotlib (>=3.7.2)
Requires-Dist: mlflow (>=2.11.3)
Requires-Dist: numpy (>=1.23.5)
Requires-Dist: optuna (>=3.6.1)
Requires-Dist: pandas (>=1.5.3)
Requires-Dist: plotly (>=5.9.0)
Requires-Dist: scikit-learn (>=1.3.0)
Requires-Dist: seaborn (>=0.12.2)
Requires-Dist: shap (>=0.44.0)
Requires-Dist: statsmodels (>=0.14.0)
Project-URL: Homepage, https://github.com/MenaWANG/mlarena
Project-URL: Repository, https://github.com/MenaWANG/mlarena
